ezipc/__init__.py
ezipc-1.0.3.dist-info/METADATA
ezipc-1.0.3.dist-info/WHEEL
ezipc-1.0.3.dist-info/df.txt
ezipc-1.0.3.dist-info/top_level.txt
ezipc-1.0.3.dist-info/RECORD
