Metadata-Version: 2.1
Name: ezipc
Version: 1.0.3
Summary: Interprocess comunication in python
Home-page: UNKNOWN
Author: Kellan Butler
Author-email: kellanbutler52@gmail.co,
License: UNKNOWN
Keywords: python,ipc
Platform: UNKNOWN
Classifier: Development Status :: 3 - Alpha
Classifier: Intended Audience :: Developers
Classifier: Programming Language :: Python :: 3
Classifier: Operating System :: MacOS :: MacOS X
Classifier: Operating System :: Microsoft :: Windows
Classifier: Operating System :: POSIX :: Linux
